pytest_filecov/__init__.py
pytest_filecov/plugin/__init__.py
pytest_filecov/plugin/gitlist.py
pytest_filecov/plugin/inotifywatcher.py
pytest_filecov/plugin/session.py
pytest_filecov/plugin/types.py
pytest_filecov-0.1.2.dist-info/LICENSE
pytest_filecov-0.1.2.dist-info/METADATA
pytest_filecov-0.1.2.dist-info/WHEEL
pytest_filecov-0.1.2.dist-info/entry_points.txt
pytest_filecov-0.1.2.dist-info/top_level.txt
pytest_filecov-0.1.2.dist-info/RECORD
