Metadata-Version: 2.1
Name: pytest-filecov
Version: 0.1.2
Summary: A pytest plugin to detect unused files
Home-page: https://github.com/rohanpm/pytest-filecov
Author: Rohan McGovern
Author-email: rohan@mcgovern.id.au
License: GNU General Public License
Platform: UNKNOWN
Classifier: Framework :: Pytest
Classifier: Development Status :: 4 - Beta
Classifier: Intended Audience :: Developers
Classifier: License :: OSI Approved :: GNU General Public License v3 or later (GPLv3+)
Classifier: Programming Language :: Python :: 3
Classifier: Topic :: Software Development :: Testing
Requires-Dist: pytest
